qiflib/__init__.py
qiflib/core/__init__.py
qiflib/core/channel.py
qiflib/core/gvulnerability.py
qiflib/core/hyper.py
qiflib/core/luncertainty.py
qiflib/core/secrets.py
qiflib/util/__init__.py
qiflib/util/probability.py
qiflib/util/types.py
qiflib-1.0.dist-info/licenses/LICENSE
qiflib-1.0.dist-info/METADATA
qiflib-1.0.dist-info/WHEEL
qiflib-1.0.dist-info/top_level.txt
qiflib-1.0.dist-info/RECORD
