Metadata-Version: 2.4
Name: qiflib
Version: 1.0
Summary: A tiny, focused Python library for Quantitative Information Flow (QIF): model secrets, channels, and analyze leakage via the g-vulnerability framework.
Home-page: https://github.com/ramongonze/qiflib
Author: Ramon Gonçalves Gonze
Author-email: Ramon Gonçalves Gonze <ramongonze@gmail.com>
License-Expression: MIT
Project-URL: Documentation, https://qiflib.readthedocs.io/
Project-URL: Repository, https://github.com/ramongonze/qiflib.git
Project-URL: Issues, https://github.com/ramongonze/qiflib/issues
Classifier: Programming Language :: Python :: 3
Classifier: Operating System :: OS Independent
Requires-Python: >=3.9
License-File: LICENSE
Requires-Dist: numpy>=1.21.5
Dynamic: author
Dynamic: home-page
Dynamic: license-file
Dynamic: requires-python
